li_common/__init__.py
li_common/helpers.py
li_common/seguranca.py
li_common/comunicacao/__init__.py
li_common/comunicacao/requisicao.py
li_common/conexoes/__init__.py
li_common/conexoes/aws.py
li_common/conexoes/cache.py
li_common/conexoes/database.py
li_common/conexoes/elasticsearch.py
li_common/conexoes/worker.py
li_common/padroes/__init__.py
li_common/padroes/cadastro.py
li_common/padroes/entidades.py
li_common/padroes/extensibilidade.py
li_common/padroes/json_encoder.py
li_common/padroes/repositorios.py
li_common/padroes/serializacao.py
li_common/padroes/servicos.py
li_common/padroes/singleton.py
li_common-1.10.dist-info/METADATA
li_common-1.10.dist-info/WHEEL
li_common-1.10.dist-info/top_level.txt
li_common-1.10.dist-info/RECORD
