Metadata-Version: 2.1
Name: li-common
Version: 1.10
Summary: Lib para funcionalidades comuns aos aplicativos da Loja Integrada
Home-page: https://github.com/lojaintegrada/LI-Common
Author: Loja Integrada
Author-email: suporte@lojaintegrada.com.br
License: MIT
Platform: UNKNOWN
Classifier: Development Status :: 2 - Pre-Alpha
Classifier: Intended Audience :: Developers
Classifier: License :: OSI Approved :: MIT License
Classifier: Operating System :: OS Independent
Classifier: Programming Language :: Python
Classifier: Programming Language :: Python :: 2.7
Classifier: Topic :: Software Development :: Libraries :: Python Modules
Classifier: Topic :: Internet
Requires-Dist: flask-restful (==0.3.4)
Requires-Dist: celery (==3.1.18)
Requires-Dist: requests (==2.7.0)
Requires-Dist: boto (==2.42.0)
Requires-Dist: pyelasticsearch (==1.4)
Requires-Dist: redis (==2.10.3)
Requires-Dist: pycrypto (==2.6.1)
Requires-Dist: jsonpickle
Requires-Dist: blinker (==1.4)
Requires-Dist: raven (==5.33.0)
Requires-Dist: selenium (==3.0.1)
